[{"params": {"tau": 0.0, "D": 0.5, "eq_perc": 0.75, "a": 0.0, "b": 1.0}, "eq_time": 0.6931683230201887}, {"params": {"tau": 0.025, "D": 0.5, "eq_perc": 0.75, "a": 0.0, "b": 1.0}, "eq_time": 0.6756672292018251}, {"params": {"tau": 0.05, "D": 0.5, "eq_perc": 0.75, "a": 0.0, "b": 1.0}, "eq_time": 0.6597287330458154}, {"params": {"tau": 0.07500000000000001, "D": 0.5, "eq_perc": 0.75, "a": 0.0, "b": 1.0}, "eq_time": 0.6447277954872179}, {"params": {"tau": 0.1, "D": 0.5, "eq_perc": 0.75, "a": 0.0, "b": 1.0}, "eq_time": 0.6306644165260329}, {"params": {"tau": 0.125, "D": 0.5, "eq_perc": 0.75, "a": 0.0, "b": 1.0}, "eq_time": 0.617851115694731}, {"params": {"tau": 0.15000000000000002, "D": 0.5, "eq_perc": 0.75, "a": 0.0, "b": 1.0}, "eq_time": 0.6062878929933121}, {"params": {"tau": 0.17500000000000002, "D": 0.5, "eq_perc": 0.75, "a": 0.0, "b": 1.0}, "eq_time": 0.5965997874867179}, {"params": {"tau": 0.2, "D": 0.5, "eq_perc": 0.75, "a": 0.0, "b": 1.0}, "eq_time": 0.5884742796424777}, {"params": {"tau": 0.225, "D": 0.5, "eq_perc": 0.75, "a": 0.0, "b": 1.0}, "eq_time": 0.5825364085255328}, {"params": {"tau": 0.25, "D": 0.5, "eq_perc": 0.75, "a": 0.0, "b": 1.0}, "eq_time": 0.5787861741358835}, {"params": {"tau": 0.275, "D": 0.5, "eq_perc": 0.75, "a": 0.0, "b": 1.0}, "eq_time": 0.5778486155384711}, {"params": {"tau": 0.30000000000000004, "D": 0.5, "eq_perc": 0.75, "a": 0.0, "b": 1.0}, "eq_time": 0.5790986936683543}, {"params": {"tau": 0.325, "D": 0.5, "eq_perc": 0.75, "a": 0.0, "b": 1.0}, "eq_time": 0.5828489280580036}, {"params": {"tau": 0.35000000000000003, "D": 0.5, "eq_perc": 0.75, "a": 0.0, "b": 1.0}, "eq_time": 0.5881617601100069}, {"params": {"tau": 0.375, "D": 0.5, "eq_perc": 0.75, "a": 0.0, "b": 1.0}, "eq_time": 0.5956622288893055}, {"params": {"tau": 0.4, "D": 0.5, "eq_perc": 0.75, "a": 0.0, "b": 1.0}, "eq_time": 0.6047252953309582}, {"params": {"tau": 0.42500000000000004, "D": 0.5, "eq_perc": 0.75, "a": 0.0, "b": 1.0}, "eq_time": 0.6150384399024938}, {"params": {"tau": 0.45, "D": 0.5, "eq_perc": 0.75, "a": 0.0, "b": 1.0}, "eq_time": 0.6269141821363835}, {"params": {"tau": 0.47500000000000003, "D": 0.5, "eq_perc": 0.75, "a": 0.0, "b": 1.0}, "eq_time": 0.640352522032627}, {"params": {"tau": 0.5, "D": 0.5, "eq_perc": 0.75, "a": 0.0, "b": 1.0}, "eq_time": 0.6547284205262829}, {"params": {"tau": 0.525, "D": 0.5, "eq_perc": 0.75, "a": 0.0, "b": 1.0}, "eq_time": 0.6706669166822926}, {"params": {"tau": 0.55, "D": 0.5, "eq_perc": 0.75, "a": 0.0, "b": 1.0}, "eq_time": 0.6878554909681855}, {"params": {"tau": 0.5750000000000001, "D": 0.5, "eq_perc": 0.75, "a": 0.0, "b": 1.0}, "eq_time": 0.7062941433839615}, {"params": {"tau": 0.6000000000000001, "D": 0.5, "eq_perc": 0.75, "a": 0.0, "b": 1.0}, "eq_time": 0.7259828739296206}, {"params": {"tau": 0.625, "D": 0.5, "eq_perc": 0.75, "a": 0.0, "b": 1.0}, "eq_time": 0.7472342021376336}, {"params": {"tau": 0.65, "D": 0.5, "eq_perc": 0.75, "a": 0.0, "b": 1.0}, "eq_time": 0.7700481280080005}, {"params": {"tau": 0.675, "D": 0.5, "eq_perc": 0.75, "a": 0.0, "b": 1.0}, "eq_time": 0.7941121320082505}, {"params": {"tau": 0.7000000000000001, "D": 0.5, "eq_perc": 0.75, "a": 0.0, "b": 1.0}, "eq_time": 0.8200512532033252}, {"params": {"tau": 0.7250000000000001, "D": 0.5, "eq_perc": 0.75, "a": 0.0, "b": 1.0}, "eq_time": 0.8475529720607538}, {"params": {"tau": 0.75, "D": 0.5, "eq_perc": 0.75, "a": 0.0, "b": 1.0}, "eq_time": 0.8772423276454778}, {"params": {"tau": 0.775, "D": 0.5, "eq_perc": 0.75, "a": 0.0, "b": 1.0}, "eq_time": 0.9094318394899681}, {"params": {"tau": 0.8, "D": 0.5, "eq_perc": 0.75, "a": 0.0, "b": 1.0}, "eq_time": 0.9441215075942246}, {"params": {"tau": 0.8250000000000001, "D": 0.5, "eq_perc": 0.75, "a": 0.0, "b": 1.0}, "eq_time": 0.981936371023189}, {"params": {"tau": 0.8500000000000001, "D": 0.5, "eq_perc": 0.75, "a": 0.0, "b": 1.0}, "eq_time": 1.0231889493093318}, {"params": {"tau": 0.875, "D": 0.5, "eq_perc": 0.75, "a": 0.0, "b": 1.0}, "eq_time": 1.0694418401150072}, {"params": {"tau": 0.9, "D": 0.5, "eq_perc": 0.75, "a": 0.0, "b": 1.0}, "eq_time": 1.1210075629726857}, {"params": {"tau": 0.925, "D": 0.5, "eq_perc": 0.75, "a": 0.0, "b": 1.0}, "eq_time": 1.1803862741421338}, {"params": {"tau": 0.9500000000000001, "D": 0.5, "eq_perc": 0.75, "a": 0.0, "b": 1.0}, "eq_time": 1.2500781298831176}, {"params": {"tau": 0.9750000000000001, "D": 0.5, "eq_perc": 0.75, "a": 0.0, "b": 1.0}, "eq_time": 1.3357084817801113}, {"params": {"tau": 1.0, "D": 0.5, "eq_perc": 0.75, "a": 0.0, "b": 1.0}, "eq_time": 1.4475904744046502}, {"params": {"tau": 1.0250000000000001, "D": 0.5, "eq_perc": 0.75, "a": 0.0, "b": 1.0}, "eq_time": 1.6376023501468842}, {"params": {"tau": 1.05, "D": 0.5, "eq_perc": 0.75, "a": 0.0, "b": 1.0}, "eq_time": 2.4976561035064693}, {"params": {"tau": 1.075, "D": 0.5, "eq_perc": 0.75, "a": 0.0, "b": 1.0}, "eq_time": 2.765172823301456}, {"params": {"tau": 1.1, "D": 0.5, "eq_perc": 0.75, "a": 0.0, "b": 1.0}, "eq_time": 2.967685480342521}, {"params": {"tau": 1.125, "D": 0.5, "eq_perc": 0.75, "a": 0.0, "b": 1.0}, "eq_time": 3.152697043565223}, {"params": {"tau": 1.1500000000000001, "D": 0.5, "eq_perc": 0.75, "a": 0.0, "b": 1.0}, "eq_time": 3.335208450528158}, {"params": {"tau": 1.175, "D": 0.5, "eq_perc": 0.75, "a": 0.0, "b": 1.0}, "eq_time": 3.5252203262703916}, {"params": {"tau": 1.2000000000000002, "D": 0.5, "eq_perc": 0.75, "a": 0.0, "b": 1.0}, "eq_time": 3.7352334520907555}, {"params": {"tau": 1.225, "D": 0.5, "eq_perc": 0.75, "a": 0.0, "b": 1.0}, "eq_time": 3.995249703106444}, {"params": {"tau": 1.25, "D": 0.5, "eq_perc": 0.75, "a": 0.0, "b": 1.0}, "eq_time": 4.437777361085068}, {"params": {"tau": 1.2750000000000001, "D": 0.5, "eq_perc": 0.75, "a": 0.0, "b": 1.0}, "eq_time": 5.860366272892056}, {"params": {"tau": 1.3, "D": 0.5, "eq_perc": 0.75, "a": 0.0, "b": 1.0}, "eq_time": 6.330395649728108}, {"params": {"tau": 1.3250000000000002, "D": 0.5, "eq_perc": 0.75, "a": 0.0, "b": 1.0}, "eq_time": 6.8129258078629915}, {"params": {"tau": 1.35, "D": 0.5, "eq_perc": 0.75, "a": 0.0, "b": 1.0}, "eq_time": 8.538033627101694}, {"params": {"tau": 1.375, "D": 0.5, "eq_perc": 0.75, "a": 0.0, "b": 1.0}, "eq_time": 9.535595974748421}, {"params": {"tau": 1.4000000000000001, "D": 0.5, "eq_perc": 0.75, "a": 0.0, "b": 1.0}, "eq_time": 11.705731608225515}, {"params": {"tau": 1.425, "D": 0.5, "eq_perc": 0.75, "a": 0.0, "b": 1.0}, "eq_time": 13.233327082942683}, {"params": {"tau": 1.4500000000000002, "D": 0.5, "eq_perc": 0.75, "a": 0.0, "b": 1.0}, "eq_time": 16.56353522095131}, {"params": {"tau": 1.475, "D": 0.5, "eq_perc": 0.75, "a": 0.0, "b": 1.0}, "eq_time": 22.116382273892118}, {"params": {"tau": 1.5, "D": 0.5, "eq_perc": 0.75, "a": 0.0, "b": 1.0}, "eq_time": 31.216951059441215}, {"params": {"tau": 0.0, "D": 0.5, "eq_perc": 0.75, "a": 1.0, "b": 1.0}, "eq_time": 0.34658416151009436}, {"params": {"tau": 0.025, "D": 0.5, "eq_perc": 0.75, "a": 1.0, "b": 1.0}, "eq_time": 0.33783361460091255}, {"params": {"tau": 0.05, "D": 0.5, "eq_perc": 0.75, "a": 1.0, "b": 1.0}, "eq_time": 0.33064566535408463}, {"params": {"tau": 0.07500000000000001, "D": 0.5, "eq_perc": 0.75, "a": 1.0, "b": 1.0}, "eq_time": 0.32439527470466906}, {"params": {"tau": 0.1, "D": 0.5, "eq_perc": 0.75, "a": 1.0, "b": 1.0}, "eq_time": 0.3190824426526658}, {"params": {"tau": 0.125, "D": 0.5, "eq_perc": 0.75, "a": 1.0, "b": 1.0}, "eq_time": 0.3156447277954872}, {"params": {"tau": 0.15000000000000002, "D": 0.5, "eq_perc": 0.75, "a": 1.0, "b": 1.0}, "eq_time": 0.31345709106819175}, {"params": {"tau": 0.17500000000000002, "D": 0.5, "eq_perc": 0.75, "a": 1.0, "b": 1.0}, "eq_time": 0.31345709106819175}, {"params": {"tau": 0.2, "D": 0.5, "eq_perc": 0.75, "a": 1.0, "b": 1.0}, "eq_time": 0.31533220826301644}, {"params": {"tau": 0.225, "D": 0.5, "eq_perc": 0.75, "a": 1.0, "b": 1.0}, "eq_time": 0.31845740358772423}, {"params": {"tau": 0.25, "D": 0.5, "eq_perc": 0.75, "a": 1.0, "b": 1.0}, "eq_time": 0.3231451965747859}, {"params": {"tau": 0.275, "D": 0.5, "eq_perc": 0.75, "a": 1.0, "b": 1.0}, "eq_time": 0.32877054815925993}, {"params": {"tau": 0.30000000000000004, "D": 0.5, "eq_perc": 0.75, "a": 1.0, "b": 1.0}, "eq_time": 0.33595849740608785}, {"params": {"tau": 0.325, "D": 0.5, "eq_perc": 0.75, "a": 1.0, "b": 1.0}, "eq_time": 0.3437714857178574}, {"params": {"tau": 0.35000000000000003, "D": 0.5, "eq_perc": 0.75, "a": 1.0, "b": 1.0}, "eq_time": 0.35283455215951}, {"params": {"tau": 0.375, "D": 0.5, "eq_perc": 0.75, "a": 1.0, "b": 1.0}, "eq_time": 0.36221013813363334}, {"params": {"tau": 0.4, "D": 0.5, "eq_perc": 0.75, "a": 1.0, "b": 1.0}, "eq_time": 0.3718982436402275}, {"params": {"tau": 0.42500000000000004, "D": 0.5, "eq_perc": 0.75, "a": 1.0, "b": 1.0}, "eq_time": 0.38189886867929246}, {"params": {"tau": 0.45, "D": 0.5, "eq_perc": 0.75, "a": 1.0, "b": 1.0}, "eq_time": 0.39221201325082816}, {"params": {"tau": 0.47500000000000003, "D": 0.5, "eq_perc": 0.75, "a": 1.0, "b": 1.0}, "eq_time": 0.40252515782236387}, {"params": {"tau": 0.5, "D": 0.5, "eq_perc": 0.75, "a": 1.0, "b": 1.0}, "eq_time": 0.41315082192637037}, {"params": {"tau": 0.525, "D": 0.5, "eq_perc": 0.75, "a": 1.0, "b": 1.0}, "eq_time": 0.4240890055628477}, {"params": {"tau": 0.55, "D": 0.5, "eq_perc": 0.75, "a": 1.0, "b": 1.0}, "eq_time": 0.4350271891993249}, {"params": {"tau": 0.5750000000000001, "D": 0.5, "eq_perc": 0.75, "a": 1.0, "b": 1.0}, "eq_time": 0.44627789236827303}, {"params": {"tau": 0.6000000000000001, "D": 0.5, "eq_perc": 0.75, "a": 1.0, "b": 1.0}, "eq_time": 0.45784111506969183}, {"params": {"tau": 0.625, "D": 0.5, "eq_perc": 0.75, "a": 1.0, "b": 1.0}, "eq_time": 0.4697168573035815}, {"params": {"tau": 0.65, "D": 0.5, "eq_perc": 0.75, "a": 1.0, "b": 1.0}, "eq_time": 0.4819051190699419}, {"params": {"tau": 0.675, "D": 0.5, "eq_perc": 0.75, "a": 1.0, "b": 1.0}, "eq_time": 0.494405900368773}, {"params": {"tau": 0.7000000000000001, "D": 0.5, "eq_perc": 0.75, "a": 1.0, "b": 1.0}, "eq_time": 0.507219201200075}, {"params": {"tau": 0.7250000000000001, "D": 0.5, "eq_perc": 0.75, "a": 1.0, "b": 1.0}, "eq_time": 0.520032502031377}, {"params": {"tau": 0.75, "D": 0.5, "eq_perc": 0.75, "a": 1.0, "b": 1.0}, "eq_time": 0.5334708419276205}, {"params": {"tau": 0.775, "D": 0.5, "eq_perc": 0.75, "a": 1.0, "b": 1.0}, "eq_time": 0.5475342208888055}, {"params": {"tau": 0.8, "D": 0.5, "eq_perc": 0.75, "a": 1.0, "b": 1.0}, "eq_time": 0.5615975998499906}, {"params": {"tau": 0.8250000000000001, "D": 0.5, "eq_perc": 0.75, "a": 1.0, "b": 1.0}, "eq_time": 0.5762860178761172}, {"params": {"tau": 0.8500000000000001, "D": 0.5, "eq_perc": 0.75, "a": 1.0, "b": 1.0}, "eq_time": 0.5912869554347147}, {"params": {"tau": 0.875, "D": 0.5, "eq_perc": 0.75, "a": 1.0, "b": 1.0}, "eq_time": 0.6069129320582536}, {"params": {"tau": 0.9, "D": 0.5, "eq_perc": 0.75, "a": 1.0, "b": 1.0}, "eq_time": 0.6228514282142634}, {"params": {"tau": 0.925, "D": 0.5, "eq_perc": 0.75, "a": 1.0, "b": 1.0}, "eq_time": 0.6394149634352146}, {"params": {"tau": 0.9500000000000001, "D": 0.5, "eq_perc": 0.75, "a": 1.0, "b": 1.0}, "eq_time": 0.6566035377211076}, {"params": {"tau": 0.9750000000000001, "D": 0.5, "eq_perc": 0.75, "a": 1.0, "b": 1.0}, "eq_time": 0.674417151071942}, {"params": {"tau": 1.0, "D": 0.5, "eq_perc": 0.75, "a": 1.0, "b": 1.0}, "eq_time": 0.6900431276954809}, {"params": {"tau": 1.0250000000000001, "D": 0.5, "eq_perc": 0.75, "a": 1.0, "b": 1.0}, "eq_time": 0.7075442215138446}, {"params": {"tau": 1.05, "D": 0.5, "eq_perc": 0.75, "a": 1.0, "b": 1.0}, "eq_time": 0.7275454715919745}, {"params": {"tau": 1.075, "D": 0.5, "eq_perc": 0.75, "a": 1.0, "b": 1.0}, "eq_time": 0.7475467216701044}, {"params": {"tau": 1.1, "D": 0.5, "eq_perc": 0.75, "a": 1.0, "b": 1.0}, "eq_time": 0.7700481280080005}, {"params": {"tau": 1.125, "D": 0.5, "eq_perc": 0.75, "a": 1.0, "b": 1.0}, "eq_time": 0.7925495343458966}, {"params": {"tau": 1.1500000000000001, "D": 0.5, "eq_perc": 0.75, "a": 1.0, "b": 1.0}, "eq_time": 0.8150509406837927}, {"params": {"tau": 1.175, "D": 0.5, "eq_perc": 0.75, "a": 1.0, "b": 1.0}, "eq_time": 0.8400525032814551}, {"params": {"tau": 1.2000000000000002, "D": 0.5, "eq_perc": 0.75, "a": 1.0, "b": 1.0}, "eq_time": 0.8650540658791174}, {"params": {"tau": 1.225, "D": 0.5, "eq_perc": 0.75, "a": 1.0, "b": 1.0}, "eq_time": 0.8925557847365461}, {"params": {"tau": 1.25, "D": 0.5, "eq_perc": 0.75, "a": 1.0, "b": 1.0}, "eq_time": 0.9225576598537408}, {"params": {"tau": 1.2750000000000001, "D": 0.5, "eq_perc": 0.75, "a": 1.0, "b": 1.0}, "eq_time": 0.9525595349709357}, {"params": {"tau": 1.3, "D": 0.5, "eq_perc": 0.75, "a": 1.0, "b": 1.0}, "eq_time": 0.9850615663478968}, {"params": {"tau": 1.3250000000000002, "D": 0.5, "eq_perc": 0.75, "a": 1.0, "b": 1.0}, "eq_time": 1.020063753984624}, {"params": {"tau": 1.35, "D": 0.5, "eq_perc": 0.75, "a": 1.0, "b": 1.0}, "eq_time": 1.0550659416213513}, {"params": {"tau": 1.375, "D": 0.5, "eq_perc": 0.75, "a": 1.0, "b": 1.0}, "eq_time": 1.0975685980373773}, {"params": {"tau": 1.4000000000000001, "D": 0.5, "eq_perc": 0.75, "a": 1.0, "b": 1.0}, "eq_time": 1.1400712544534033}, {"params": {"tau": 1.425, "D": 0.5, "eq_perc": 0.75, "a": 1.0, "b": 1.0}, "eq_time": 1.1875742233889617}, {"params": {"tau": 1.4500000000000002, "D": 0.5, "eq_perc": 0.75, "a": 1.0, "b": 1.0}, "eq_time": 1.2400775048440527}, {"params": {"tau": 1.475, "D": 0.5, "eq_perc": 0.75, "a": 1.0, "b": 1.0}, "eq_time": 1.3000812550784424}, {"params": {"tau": 1.5, "D": 0.5, "eq_perc": 0.75, "a": 1.0, "b": 1.0}, "eq_time": 1.3675854740921307}, {"params": {"tau": 1.5250000000000001, "D": 0.5, "eq_perc": 0.75, "a": 1.0, "b": 1.0}, "eq_time": 1.445090318144884}, {"params": {"tau": 1.55, "D": 0.5, "eq_perc": 0.75, "a": 1.0, "b": 1.0}, "eq_time": 1.5375960997562348}, {"params": {"tau": 1.5750000000000002, "D": 0.5, "eq_perc": 0.75, "a": 1.0, "b": 1.0}, "eq_time": 1.902618913682105}, {"params": {"tau": 1.6, "D": 0.5, "eq_perc": 0.75, "a": 1.0, "b": 1.0}, "eq_time": 2.112632039502469}, {"params": {"tau": 1.625, "D": 0.5, "eq_perc": 0.75, "a": 1.0, "b": 1.0}, "eq_time": 2.2226389149321832}, {"params": {"tau": 1.6500000000000001, "D": 0.5, "eq_perc": 0.75, "a": 1.0, "b": 1.0}, "eq_time": 2.315144696543534}, {"params": {"tau": 1.675, "D": 0.5, "eq_perc": 0.75, "a": 1.0, "b": 1.0}, "eq_time": 2.3951496968560533}, {"params": {"tau": 1.7000000000000002, "D": 0.5, "eq_perc": 0.75, "a": 1.0, "b": 1.0}, "eq_time": 2.4701543846490406}, {"params": {"tau": 1.725, "D": 0.5, "eq_perc": 0.75, "a": 1.0, "b": 1.0}, "eq_time": 2.540158759922495}, {"params": {"tau": 1.75, "D": 0.5, "eq_perc": 0.75, "a": 1.0, "b": 1.0}, "eq_time": 2.6076629789361836}, {"params": {"tau": 1.7750000000000001, "D": 0.5, "eq_perc": 0.75, "a": 1.0, "b": 1.0}, "eq_time": 2.6726670416901057}, {"params": {"tau": 1.8, "D": 0.5, "eq_perc": 0.75, "a": 1.0, "b": 1.0}, "eq_time": 2.7351709481842614}, {"params": {"tau": 1.8250000000000002, "D": 0.5, "eq_perc": 0.75, "a": 1.0, "b": 1.0}, "eq_time": 2.797674854678417}, {"params": {"tau": 1.85, "D": 0.5, "eq_perc": 0.75, "a": 1.0, "b": 1.0}, "eq_time": 2.857678604912807}, {"params": {"tau": 1.875, "D": 0.5, "eq_perc": 0.75, "a": 1.0, "b": 1.0}, "eq_time": 2.9176823551471966}, {"params": {"tau": 1.9000000000000001, "D": 0.5, "eq_perc": 0.75, "a": 1.0, "b": 1.0}, "eq_time": 2.9776861053815864}, {"params": {"tau": 1.925, "D": 0.5, "eq_perc": 0.75, "a": 1.0, "b": 1.0}, "eq_time": 3.037689855615976}, {"params": {"tau": 1.9500000000000002, "D": 0.5, "eq_perc": 0.75, "a": 1.0, "b": 1.0}, "eq_time": 3.0951934495905995}, {"params": {"tau": 1.975, "D": 0.5, "eq_perc": 0.75, "a": 1.0, "b": 1.0}, "eq_time": 3.155197199824989}, {"params": {"tau": 2.0, "D": 0.5, "eq_perc": 0.75, "a": 1.0, "b": 1.0}, "eq_time": 3.2127007937996126}, {"params": {"tau": 2.025, "D": 0.5, "eq_perc": 0.75, "a": 1.0, "b": 1.0}, "eq_time": 3.272704544034002}, {"params": {"tau": 2.0500000000000003, "D": 0.5, "eq_perc": 0.75, "a": 1.0, "b": 1.0}, "eq_time": 3.3327082942683917}, {"params": {"tau": 2.075, "D": 0.5, "eq_perc": 0.75, "a": 1.0, "b": 1.0}, "eq_time": 3.390211888243015}, {"params": {"tau": 2.1, "D": 0.5, "eq_perc": 0.75, "a": 1.0, "b": 1.0}, "eq_time": 3.4502156384774048}, {"params": {"tau": 0.1, "D": 0.045, "eq_perc": 0.75, "a": 0, "b": 1}, "eq_time": 0.6306644165260329}, {"params": {"tau": 0.0, "D": 0.045, "eq_perc": 0.75, "a": 0, "b": 1}, "eq_time": 0.6931683230201887}, {"params": {"tau": 0.05, "D": 0.045, "eq_perc": 0.75, "a": 0, "b": 1}, "eq_time": 0.6597287330458154}, {"params": {"tau": 0.2, "D": 0.045, "eq_perc": 0.75, "a": 0, "b": 1}, "eq_time": 0.5884742796424777}, {"params": {"tau": 0.4, "D": 0.045, "eq_perc": 0.75, "a": 0, "b": 1}, "eq_time": 0.6047252953309582}, {"params": {"tau": 0.6000000000000001, "D": 0.045, "eq_perc": 0.75, "a": 0, "b": 1}, "eq_time": 0.7259828739296206}, {"params": {"tau": 0.8, "D": 0.045, "eq_perc": 0.75, "a": 0, "b": 1}, "eq_time": 0.9441215075942246}, {"params": {"tau": 1.0, "D": 0.045, "eq_perc": 0.75, "a": 0, "b": 1}, "eq_time": 1.4475904744046502}, {"params": {"tau": 1.2, "D": 0.045, "eq_perc": 0.75, "a": 0, "b": 1}, "eq_time": 3.7352334520907555}, {"params": {"tau": 1.4000000000000001, "D": 0.045, "eq_perc": 0.75, "a": 0, "b": 1}, "eq_time": 11.705731608225515}, {"params": {"tau": 1.6, "D": 0.045, "eq_perc": 0.75, "a": 0, "b": 1}, "eq_time": -1}, {"params": {"tau": 1.8, "D": 0.045, "eq_perc": 0.75, "a": 0, "b": 1}, "eq_time": -1}, {"params": {"tau": 2.0, "D": 0.045, "eq_perc": 0.75, "a": 0, "b": 1}, "eq_time": -1}, {"params": {"tau": 0.0, "D": 0.020000000000000004, "eq_perc": 0.75, "a": 0, "b": 1}, "eq_time": 0.6931683230201887}, {"params": {"tau": 0.05, "D": 0.020000000000000004, "eq_perc": 0.75, "a": 0, "b": 1}, "eq_time": 0.6597287330458154}, {"params": {"tau": 0.2, "D": 0.020000000000000004, "eq_perc": 0.75, "a": 0, "b": 1}, "eq_time": 0.5884742796424777}, {"params": {"tau": 0.4, "D": 0.020000000000000004, "eq_perc": 0.75, "a": 0, "b": 1}, "eq_time": 0.6047252953309582}, {"params": {"tau": 0.6000000000000001, "D": 0.020000000000000004, "eq_perc": 0.75, "a": 0, "b": 1}, "eq_time": 0.7259828739296206}, {"params": {"tau": 0.8, "D": 0.020000000000000004, "eq_perc": 0.75, "a": 0, "b": 1}, "eq_time": 0.9441215075942246}, {"params": {"tau": 1.0, "D": 0.020000000000000004, "eq_perc": 0.75, "a": 0, "b": 1}, "eq_time": 1.4475904744046502}, {"params": {"tau": 1.2, "D": 0.020000000000000004, "eq_perc": 0.75, "a": 0, "b": 1}, "eq_time": 3.7352334520907555}, {"params": {"tau": 1.4000000000000001, "D": 0.020000000000000004, "eq_perc": 0.75, "a": 0, "b": 1}, "eq_time": 11.705731608225515}, {"params": {"tau": 0.0, "D": 0.04500000000000001, "eq_perc": 0.75, "a": 0, "b": 1}, "eq_time": 0.6931683230201887}, {"params": {"tau": 0.05, "D": 0.04500000000000001, "eq_perc": 0.75, "a": 0, "b": 1}, "eq_time": 0.6597287330458154}, {"params": {"tau": 0.2, "D": 0.04500000000000001, "eq_perc": 0.75, "a": 0, "b": 1}, "eq_time": 0.5884742796424777}, {"params": {"tau": 0.4, "D": 0.04500000000000001, "eq_perc": 0.75, "a": 0, "b": 1}, "eq_time": 0.6047252953309582}, {"params": {"tau": 0.6000000000000001, "D": 0.04500000000000001, "eq_perc": 0.75, "a": 0, "b": 1}, "eq_time": 0.7259828739296206}, {"params": {"tau": 0.8, "D": 0.04500000000000001, "eq_perc": 0.75, "a": 0, "b": 1}, "eq_time": 0.9441215075942246}, {"params": {"tau": 1.0, "D": 0.04500000000000001, "eq_perc": 0.75, "a": 0, "b": 1}, "eq_time": 1.4475904744046502}, {"params": {"tau": 1.2, "D": 0.04500000000000001, "eq_perc": 0.75, "a": 0, "b": 1}, "eq_time": 3.7352334520907555}, {"params": {"tau": 1.4000000000000001, "D": 0.04500000000000001, "eq_perc": 0.75, "a": 0, "b": 1}, "eq_time": 11.705731608225515}, {"params": {"tau": 0.0, "D": 0.08000000000000003, "eq_perc": 0.75, "a": 0, "b": 1}, "eq_time": 0.6931683230201887}, {"params": {"tau": 0.05, "D": 0.08000000000000003, "eq_perc": 0.75, "a": 0, "b": 1}, "eq_time": 0.6597287330458154}, {"params": {"tau": 0.2, "D": 0.08000000000000003, "eq_perc": 0.75, "a": 0, "b": 1}, "eq_time": 0.5884742796424777}, {"params": {"tau": 0.4, "D": 0.08000000000000003, "eq_perc": 0.75, "a": 0, "b": 1}, "eq_time": 0.6047252953309582}, {"params": {"tau": 0.6000000000000001, "D": 0.08000000000000003, "eq_perc": 0.75, "a": 0, "b": 1}, "eq_time": 0.7259828739296206}, {"params": {"tau": 0.8, "D": 0.08000000000000003, "eq_perc": 0.75, "a": 0, "b": 1}, "eq_time": 0.9441215075942246}, {"params": {"tau": 1.0, "D": 0.08000000000000003, "eq_perc": 0.75, "a": 0, "b": 1}, "eq_time": 1.4475904744046502}, {"params": {"tau": 1.2, "D": 0.08000000000000003, "eq_perc": 0.75, "a": 0, "b": 1}, "eq_time": 3.7352334520907555}, {"params": {"tau": 1.4000000000000001, "D": 0.08000000000000003, "eq_perc": 0.75, "a": 0, "b": 1}, "eq_time": 11.705731608225515}, {"params": {"tau": 0.0, "D": 0.12500000000000006, "eq_perc": 0.75, "a": 0, "b": 1}, "eq_time": 0.6931683230201887}, {"params": {"tau": 0.05, "D": 0.12500000000000006, "eq_perc": 0.75, "a": 0, "b": 1}, "eq_time": 0.6597287330458154}, {"params": {"tau": 0.2, "D": 0.12500000000000006, "eq_perc": 0.75, "a": 0, "b": 1}, "eq_time": 0.5884742796424777}, {"params": {"tau": 0.4, "D": 0.12500000000000006, "eq_perc": 0.75, "a": 0, "b": 1}, "eq_time": 0.6047252953309582}, {"params": {"tau": 0.6000000000000001, "D": 0.12500000000000006, "eq_perc": 0.75, "a": 0, "b": 1}, "eq_time": 0.7259828739296206}, {"params": {"tau": 0.8, "D": 0.12500000000000006, "eq_perc": 0.75, "a": 0, "b": 1}, "eq_time": 0.9441215075942246}, {"params": {"tau": 1.0, "D": 0.12500000000000006, "eq_perc": 0.75, "a": 0, "b": 1}, "eq_time": 1.4475904744046502}, {"params": {"tau": 1.2, "D": 0.12500000000000006, "eq_perc": 0.75, "a": 0, "b": 1}, "eq_time": 3.7352334520907555}, {"params": {"tau": 1.4000000000000001, "D": 0.12500000000000006, "eq_perc": 0.75, "a": 0, "b": 1}, "eq_time": 11.705731608225515}, {"params": {"tau": 0.0, "D": 0.18000000000000005, "eq_perc": 0.75, "a": 0, "b": 1}, "eq_time": 0.6931683230201887}, {"params": {"tau": 0.05, "D": 0.18000000000000005, "eq_perc": 0.75, "a": 0, "b": 1}, "eq_time": 0.6597287330458154}, {"params": {"tau": 0.2, "D": 0.18000000000000005, "eq_perc": 0.75, "a": 0, "b": 1}, "eq_time": 0.5884742796424777}, {"params": {"tau": 0.4, "D": 0.18000000000000005, "eq_perc": 0.75, "a": 0, "b": 1}, "eq_time": 0.6047252953309582}, {"params": {"tau": 0.6000000000000001, "D": 0.18000000000000005, "eq_perc": 0.75, "a": 0, "b": 1}, "eq_time": 0.7259828739296206}, {"params": {"tau": 0.8, "D": 0.18000000000000005, "eq_perc": 0.75, "a": 0, "b": 1}, "eq_time": 0.9441215075942246}, {"params": {"tau": 1.0, "D": 0.18000000000000005, "eq_perc": 0.75, "a": 0, "b": 1}, "eq_time": 1.4475904744046502}, {"params": {"tau": 1.2, "D": 0.18000000000000005, "eq_perc": 0.75, "a": 0, "b": 1}, "eq_time": 3.7352334520907555}, {"params": {"tau": 1.4000000000000001, "D": 0.18000000000000005, "eq_perc": 0.75, "a": 0, "b": 1}, "eq_time": 11.705731608225515}, {"params": {"tau": 0.0, "D": 0.24500000000000013, "eq_perc": 0.75, "a": 0, "b": 1}, "eq_time": 0.6931683230201887}, {"params": {"tau": 0.05, "D": 0.24500000000000013, "eq_perc": 0.75, "a": 0, "b": 1}, "eq_time": 0.6597287330458154}, {"params": {"tau": 0.2, "D": 0.24500000000000013, "eq_perc": 0.75, "a": 0, "b": 1}, "eq_time": 0.5884742796424777}, {"params": {"tau": 0.4, "D": 0.24500000000000013, "eq_perc": 0.75, "a": 0, "b": 1}, "eq_time": 0.6047252953309582}, {"params": {"tau": 0.6000000000000001, "D": 0.24500000000000013, "eq_perc": 0.75, "a": 0, "b": 1}, "eq_time": 0.7259828739296206}, {"params": {"tau": 0.8, "D": 0.24500000000000013, "eq_perc": 0.75, "a": 0, "b": 1}, "eq_time": 0.9441215075942246}, {"params": {"tau": 1.0, "D": 0.24500000000000013, "eq_perc": 0.75, "a": 0, "b": 1}, "eq_time": 1.4475904744046502}, {"params": {"tau": 1.2, "D": 0.24500000000000013, "eq_perc": 0.75, "a": 0, "b": 1}, "eq_time": 3.7352334520907555}, {"params": {"tau": 1.4000000000000001, "D": 0.24500000000000013, "eq_perc": 0.75, "a": 0, "b": 1}, "eq_time": 11.705731608225515}, {"params": {"tau": 0.0, "D": 0.32000000000000023, "eq_perc": 0.75, "a": 0, "b": 1}, "eq_time": 0.6931683230201887}, {"params": {"tau": 0.05, "D": 0.32000000000000023, "eq_perc": 0.75, "a": 0, "b": 1}, "eq_time": 0.6597287330458154}, {"params": {"tau": 0.2, "D": 0.32000000000000023, "eq_perc": 0.75, "a": 0, "b": 1}, "eq_time": 0.5884742796424777}, {"params": {"tau": 0.4, "D": 0.32000000000000023, "eq_perc": 0.75, "a": 0, "b": 1}, "eq_time": 0.6047252953309582}, {"params": {"tau": 0.6000000000000001, "D": 0.32000000000000023, "eq_perc": 0.75, "a": 0, "b": 1}, "eq_time": 0.7259828739296206}, {"params": {"tau": 0.8, "D": 0.32000000000000023, "eq_perc": 0.75, "a": 0, "b": 1}, "eq_time": 0.9441215075942246}, {"params": {"tau": 1.0, "D": 0.32000000000000023, "eq_perc": 0.75, "a": 0, "b": 1}, "eq_time": 1.4475904744046502}, {"params": {"tau": 1.2, "D": 0.32000000000000023, "eq_perc": 0.75, "a": 0, "b": 1}, "eq_time": 3.7352334520907555}, {"params": {"tau": 1.4000000000000001, "D": 0.32000000000000023, "eq_perc": 0.75, "a": 0, "b": 1}, "eq_time": 11.705731608225515}, {"params": {"tau": 0, "D": 0.022050000000000004, "eq_perc": 0.75, "a": 0, "b": 1}, "eq_time": 0.6931683230201887}, {"params": {"tau": 0, "D": 0.0288, "eq_perc": 0.75, "a": 0, "b": 1}, "eq_time": 0.6931683230201887}, {"params": {"tau": 0, "D": 0.03919999999999999, "eq_perc": 0.75, "a": 0, "b": 1}, "eq_time": 0.6931683230201887}, {"params": {"tau": 0, "D": 0.05120000000000002, "eq_perc": 0.75, "a": 0, "b": 1}, "eq_time": 0.6931683230201887}, {"params": {"tau": 0, "D": 0.06480000000000001, "eq_perc": 0.75, "a": 0, "b": 1}, "eq_time": 0.6931683230201887}, {"params": {"tau": 0, "D": 0.08000000000000002, "eq_perc": 0.75, "a": 0, "b": 1}, "eq_time": 0.6931683230201887}, {"params": {"tau": 0, "D": 0.09680000000000002, "eq_perc": 0.75, "a": 0, "b": 1}, "eq_time": 0.6931683230201887}, {"params": {"tau": 0, "D": 0.11520000000000004, "eq_perc": 0.75, "a": 0, "b": 1}, "eq_time": 0.6931683230201887}, {"params": {"tau": 0, "D": 0.04961250000000002, "eq_perc": 0.75, "a": 0, "b": 1}, "eq_time": 0.6931683230201887}, {"params": {"tau": 0, "D": 0.08820000000000001, "eq_perc": 0.75, "a": 0, "b": 1}, "eq_time": 0.6931683230201887}, {"params": {"tau": 0, "D": 0.14580000000000007, "eq_perc": 0.75, "a": 0, "b": 1}, "eq_time": 0.6931683230201887}, {"params": {"tau": 0, "D": 0.2178000000000001, "eq_perc": 0.75, "a": 0, "b": 1}, "eq_time": 0.6931683230201887}, {"params": {"tau": 0, "D": 0.25920000000000015, "eq_perc": 0.75, "a": 0, "b": 1}, "eq_time": 0.6931683230201887}, {"params": {"tau": 0, "D": 0.08820000000000004, "eq_perc": 0.75, "a": 0, "b": 1}, "eq_time": 0.6931683230201887}, {"params": {"tau": 0, "D": 0.15680000000000002, "eq_perc": 0.75, "a": 0, "b": 1}, "eq_time": 0.6931683230201887}, {"params": {"tau": 0, "D": 0.2048000000000001, "eq_perc": 0.75, "a": 0, "b": 1}, "eq_time": 0.6931683230201887}, {"params": {"tau": 0, "D": 0.3200000000000001, "eq_perc": 0.75, "a": 0, "b": 1}, "eq_time": 0.6931683230201887}, {"params": {"tau": 0, "D": 0.3872000000000002, "eq_perc": 0.75, "a": 0, "b": 1}, "eq_time": 0.6931683230201887}, {"params": {"tau": 0, "D": 0.46080000000000026, "eq_perc": 0.75, "a": 0, "b": 1}, "eq_time": 0.6931683230201887}, {"params": {"tau": 0, "D": 0.13781250000000006, "eq_perc": 0.75, "a": 0, "b": 1}, "eq_time": 0.6931683230201887}, {"params": {"tau": 0, "D": 0.24500000000000005, "eq_perc": 0.75, "a": 0, "b": 1}, "eq_time": 0.6931683230201887}, {"params": {"tau": 0, "D": 0.4050000000000002, "eq_perc": 0.75, "a": 0, "b": 1}, "eq_time": 0.6931683230201887}, {"params": {"tau": 0, "D": 0.5000000000000002, "eq_perc": 0.75, "a": 0, "b": 1}, "eq_time": 0.6931683230201887}, {"params": {"tau": 0, "D": 0.6050000000000003, "eq_perc": 0.75, "a": 0, "b": 1}, "eq_time": 0.6931683230201887}, {"params": {"tau": 0, "D": 0.7200000000000005, "eq_perc": 0.75, "a": 0, "b": 1}, "eq_time": 0.6931683230201887}, {"params": {"tau": 0, "D": 0.19845000000000007, "eq_perc": 0.75, "a": 0, "b": 1}, "eq_time": 0.6931683230201887}, {"params": {"tau": 0, "D": 0.25920000000000004, "eq_perc": 0.75, "a": 0, "b": 1}, "eq_time": 0.6931683230201887}, {"params": {"tau": 0, "D": 0.35280000000000006, "eq_perc": 0.75, "a": 0, "b": 1}, "eq_time": 0.6931683230201887}, {"params": {"tau": 0, "D": 0.46080000000000015, "eq_perc": 0.75, "a": 0, "b": 1}, "eq_time": 0.6931683230201887}, {"params": {"tau": 0, "D": 0.5832000000000003, "eq_perc": 0.75, "a": 0, "b": 1}, "eq_time": 0.6931683230201887}, {"params": {"tau": 0, "D": 0.7200000000000002, "eq_perc": 0.75, "a": 0, "b": 1}, "eq_time": 0.6931683230201887}, {"params": {"tau": 0, "D": 0.8712000000000004, "eq_perc": 0.75, "a": 0, "b": 1}, "eq_time": 0.6931683230201887}, {"params": {"tau": 0, "D": 1.0368000000000006, "eq_perc": 0.75, "a": 0, "b": 1}, "eq_time": 0.6931683230201887}, {"params": {"tau": 0, "D": 0.27011250000000014, "eq_perc": 0.75, "a": 0, "b": 1}, "eq_time": 0.6931683230201887}, {"params": {"tau": 0, "D": 0.35280000000000017, "eq_perc": 0.75, "a": 0, "b": 1}, "eq_time": 0.6931683230201887}, {"params": {"tau": 0, "D": 0.4802000000000002, "eq_perc": 0.75, "a": 0, "b": 1}, "eq_time": 0.6931683230201887}, {"params": {"tau": 0, "D": 0.6272000000000003, "eq_perc": 0.75, "a": 0, "b": 1}, "eq_time": 0.6931683230201887}, {"params": {"tau": 0, "D": 0.7938000000000006, "eq_perc": 0.75, "a": 0, "b": 1}, "eq_time": 0.6931683230201887}, {"params": {"tau": 0, "D": 0.9800000000000005, "eq_perc": 0.75, "a": 0, "b": 1}, "eq_time": 0.6931683230201887}, {"params": {"tau": 0, "D": 1.1858000000000006, "eq_perc": 0.75, "a": 0, "b": 1}, "eq_time": 0.6931683230201887}, {"params": {"tau": 0, "D": 1.4112000000000011, "eq_perc": 0.75, "a": 0, "b": 1}, "eq_time": 0.6931683230201887}, {"params": {"tau": 0, "D": 0.3528000000000003, "eq_perc": 0.75, "a": 0, "b": 1}, "eq_time": 0.6931683230201887}, {"params": {"tau": 0, "D": 0.8192000000000006, "eq_perc": 0.75, "a": 0, "b": 1}, "eq_time": 0.6931683230201887}, {"params": {"tau": 0, "D": 1.0368000000000008, "eq_perc": 0.75, "a": 0, "b": 1}, "eq_time": 0.6931683230201887}, {"params": {"tau": 0, "D": 1.280000000000001, "eq_perc": 0.75, "a": 0, "b": 1}, "eq_time": 0.6931683230201887}, {"params": {"tau": 0, "D": 1.5488000000000013, "eq_perc": 0.75, "a": 0, "b": 1}, "eq_time": 0.6931683230201887}, {"params": {"tau": 0, "D": 1.8432000000000015, "eq_perc": 0.75, "a": 0, "b": 1}, "eq_time": 0.6931683230201887}, {"params": {"tau": 0, "D": 0.021, "eq_perc": 0.75, "a": 0, "b": 1}, "eq_time": 0.6931683230201887}, {"params": {"tau": 0, "D": 0.024, "eq_perc": 0.75, "a": 0, "b": 1}, "eq_time": 0.6931683230201887}, {"params": {"tau": 0, "D": 0.027999999999999994, "eq_perc": 0.75, "a": 0, "b": 1}, "eq_time": 0.6931683230201887}, {"params": {"tau": 0, "D": 0.03200000000000001, "eq_perc": 0.75, "a": 0, "b": 1}, "eq_time": 0.6931683230201887}, {"params": {"tau": 0, "D": 0.036000000000000004, "eq_perc": 0.75, "a": 0, "b": 1}, "eq_time": 0.6931683230201887}, {"params": {"tau": 0, "D": 0.04, "eq_perc": 0.75, "a": 0, "b": 1}, "eq_time": 0.6931683230201887}, {"params": {"tau": 0, "D": 0.04400000000000001, "eq_perc": 0.75, "a": 0, "b": 1}, "eq_time": 0.6931683230201887}, {"params": {"tau": 0, "D": 0.048000000000000015, "eq_perc": 0.75, "a": 0, "b": 1}, "eq_time": 0.6931683230201887}, {"params": {"tau": 0, "D": 0.04725, "eq_perc": 0.75, "a": 0, "b": 1}, "eq_time": 0.6931683230201887}, {"params": {"tau": 0, "D": 0.05400000000000002, "eq_perc": 0.75, "a": 0, "b": 1}, "eq_time": 0.6931683230201887}, {"params": {"tau": 0, "D": 0.06300000000000001, "eq_perc": 0.75, "a": 0, "b": 1}, "eq_time": 0.6931683230201887}, {"params": {"tau": 0, "D": 0.07200000000000004, "eq_perc": 0.75, "a": 0, "b": 1}, "eq_time": 0.6931683230201887}, {"params": {"tau": 0, "D": 0.08100000000000004, "eq_perc": 0.75, "a": 0, "b": 1}, "eq_time": 0.6931683230201887}, {"params": {"tau": 0, "D": 0.09000000000000002, "eq_perc": 0.75, "a": 0, "b": 1}, "eq_time": 0.6931683230201887}, {"params": {"tau": 0, "D": 0.09900000000000005, "eq_perc": 0.75, "a": 0, "b": 1}, "eq_time": 0.6931683230201887}, {"params": {"tau": 0, "D": 0.10800000000000004, "eq_perc": 0.75, "a": 0, "b": 1}, "eq_time": 0.6931683230201887}, {"params": {"tau": 0, "D": 0.08400000000000003, "eq_perc": 0.75, "a": 0, "b": 1}, "eq_time": 0.6931683230201887}, {"params": {"tau": 0, "D": 0.09600000000000006, "eq_perc": 0.75, "a": 0, "b": 1}, "eq_time": 0.6931683230201887}, {"params": {"tau": 0, "D": 0.11200000000000003, "eq_perc": 0.75, "a": 0, "b": 1}, "eq_time": 0.6931683230201887}, {"params": {"tau": 0, "D": 0.12800000000000003, "eq_perc": 0.75, "a": 0, "b": 1}, "eq_time": 0.6931683230201887}, {"params": {"tau": 0, "D": 0.14400000000000007, "eq_perc": 0.75, "a": 0, "b": 1}, "eq_time": 0.6931683230201887}, {"params": {"tau": 0, "D": 0.16000000000000006, "eq_perc": 0.75, "a": 0, "b": 1}, "eq_time": 0.6931683230201887}, {"params": {"tau": 0, "D": 0.17600000000000005, "eq_perc": 0.75, "a": 0, "b": 1}, "eq_time": 0.6931683230201887}, {"params": {"tau": 0, "D": 0.19200000000000014, "eq_perc": 0.75, "a": 0, "b": 1}, "eq_time": 0.6931683230201887}, {"params": {"tau": 0, "D": 0.13125000000000003, "eq_perc": 0.75, "a": 0, "b": 1}, "eq_time": 0.6931683230201887}, {"params": {"tau": 0, "D": 0.15000000000000005, "eq_perc": 0.75, "a": 0, "b": 1}, "eq_time": 0.6931683230201887}, {"params": {"tau": 0, "D": 0.17500000000000004, "eq_perc": 0.75, "a": 0, "b": 1}, "eq_time": 0.6931683230201887}, {"params": {"tau": 0, "D": 0.20000000000000015, "eq_perc": 0.75, "a": 0, "b": 1}, "eq_time": 0.6931683230201887}, {"params": {"tau": 0, "D": 0.2250000000000001, "eq_perc": 0.75, "a": 0, "b": 1}, "eq_time": 0.6931683230201887}, {"params": {"tau": 0, "D": 0.2500000000000001, "eq_perc": 0.75, "a": 0, "b": 1}, "eq_time": 0.6931683230201887}, {"params": {"tau": 0, "D": 0.2750000000000001, "eq_perc": 0.75, "a": 0, "b": 1}, "eq_time": 0.6931683230201887}, {"params": {"tau": 0, "D": 0.3000000000000002, "eq_perc": 0.75, "a": 0, "b": 1}, "eq_time": 0.6931683230201887}, {"params": {"tau": 0, "D": 0.189, "eq_perc": 0.75, "a": 0, "b": 1}, "eq_time": 0.6931683230201887}, {"params": {"tau": 0, "D": 0.21600000000000008, "eq_perc": 0.75, "a": 0, "b": 1}, "eq_time": 0.6931683230201887}, {"params": {"tau": 0, "D": 0.25200000000000006, "eq_perc": 0.75, "a": 0, "b": 1}, "eq_time": 0.6931683230201887}, {"params": {"tau": 0, "D": 0.28800000000000014, "eq_perc": 0.75, "a": 0, "b": 1}, "eq_time": 0.6931683230201887}, {"params": {"tau": 0, "D": 0.3240000000000002, "eq_perc": 0.75, "a": 0, "b": 1}, "eq_time": 0.6931683230201887}, {"params": {"tau": 0, "D": 0.3600000000000001, "eq_perc": 0.75, "a": 0, "b": 1}, "eq_time": 0.6931683230201887}, {"params": {"tau": 0, "D": 0.3960000000000002, "eq_perc": 0.75, "a": 0, "b": 1}, "eq_time": 0.6931683230201887}, {"params": {"tau": 0, "D": 0.43200000000000016, "eq_perc": 0.75, "a": 0, "b": 1}, "eq_time": 0.6931683230201887}, {"params": {"tau": 0, "D": 0.2572500000000001, "eq_perc": 0.75, "a": 0, "b": 1}, "eq_time": 0.6931683230201887}, {"params": {"tau": 0, "D": 0.29400000000000015, "eq_perc": 0.75, "a": 0, "b": 1}, "eq_time": 0.6931683230201887}, {"params": {"tau": 0, "D": 0.34300000000000014, "eq_perc": 0.75, "a": 0, "b": 1}, "eq_time": 0.6931683230201887}, {"params": {"tau": 0, "D": 0.3920000000000002, "eq_perc": 0.75, "a": 0, "b": 1}, "eq_time": 0.6931683230201887}, {"params": {"tau": 0, "D": 0.4410000000000003, "eq_perc": 0.75, "a": 0, "b": 1}, "eq_time": 0.6931683230201887}, {"params": {"tau": 0, "D": 0.49000000000000016, "eq_perc": 0.75, "a": 0, "b": 1}, "eq_time": 0.6931683230201887}, {"params": {"tau": 0, "D": 0.5390000000000003, "eq_perc": 0.75, "a": 0, "b": 1}, "eq_time": 0.6931683230201887}, {"params": {"tau": 0, "D": 0.5880000000000003, "eq_perc": 0.75, "a": 0, "b": 1}, "eq_time": 0.6931683230201887}, {"params": {"tau": 0, "D": 0.33600000000000024, "eq_perc": 0.75, "a": 0, "b": 1}, "eq_time": 0.6931683230201887}, {"params": {"tau": 0, "D": 0.38400000000000034, "eq_perc": 0.75, "a": 0, "b": 1}, "eq_time": 0.6931683230201887}, {"params": {"tau": 0, "D": 0.44800000000000023, "eq_perc": 0.75, "a": 0, "b": 1}, "eq_time": 0.6931683230201887}, {"params": {"tau": 0, "D": 0.5120000000000003, "eq_perc": 0.75, "a": 0, "b": 1}, "eq_time": 0.6931683230201887}, {"params": {"tau": 0, "D": 0.5760000000000005, "eq_perc": 0.75, "a": 0, "b": 1}, "eq_time": 0.6931683230201887}, {"params": {"tau": 0, "D": 0.6400000000000002, "eq_perc": 0.75, "a": 0, "b": 1}, "eq_time": 0.6931683230201887}, {"params": {"tau": 0, "D": 0.7040000000000005, "eq_perc": 0.75, "a": 0, "b": 1}, "eq_time": 0.6931683230201887}, {"params": {"tau": 0, "D": 0.7680000000000006, "eq_perc": 0.75, "a": 0, "b": 1}, "eq_time": 0.6931683230201887}, {"params": {"tau": 0, "D": 0.021025860235679997, "eq_perc": 0.75, "a": 0, "b": 1}, "eq_time": 0.6931683230201887}, {"params": {"tau": 0, "D": 0.024460977608997306, "eq_perc": 0.75, "a": 0, "b": 1}, "eq_time": 0.6931683230201887}, {"params": {"tau": 0, "D": 0.03016995294242801, "eq_perc": 0.75, "a": 0, "b": 1}, "eq_time": 0.6931683230201887}, {"params": {"tau": 0, "D": 0.03791530245708019, "eq_perc": 0.75, "a": 0, "b": 1}, "eq_time": 0.6931683230201887}, {"params": {"tau": 0, "D": 0.04929925513445208, "eq_perc": 0.75, "a": 0, "b": 1}, "eq_time": 0.6931683230201887}, {"params": {"tau": 0, "D": 0.06816446884671656, "eq_perc": 0.75, "a": 0, "b": 1}, "eq_time": 0.6931683230201887}, {"params": {"tau": 0, "D": 0.10663710446917449, "eq_perc": 0.75, "a": 0, "b": 1}, "eq_time": 0.6931683230201887}, {"params": {"tau": 0, "D": 0.23362747600620495, "eq_perc": 0.75, "a": 0, "b": 1}, "eq_time": 0.6931683230201887}, {"params": {"tau": 0, "D": 0.04730818553028002, "eq_perc": 0.75, "a": 0, "b": 1}, "eq_time": 0.6931683230201887}, {"params": {"tau": 0, "D": 0.05503719962024395, "eq_perc": 0.75, "a": 0, "b": 1}, "eq_time": 0.6931683230201887}, {"params": {"tau": 0, "D": 0.06788239412046304, "eq_perc": 0.75, "a": 0, "b": 1}, "eq_time": 0.6931683230201887}, {"params": {"tau": 0, "D": 0.08530943052843046, "eq_perc": 0.75, "a": 0, "b": 1}, "eq_time": 0.6931683230201887}, {"params": {"tau": 0, "D": 0.11092332405251722, "eq_perc": 0.75, "a": 0, "b": 1}, "eq_time": 0.6931683230201887}, {"params": {"tau": 0, "D": 0.1533700549051123, "eq_perc": 0.75, "a": 0, "b": 1}, "eq_time": 0.6931683230201887}, {"params": {"tau": 0, "D": 0.23993348505564263, "eq_perc": 0.75, "a": 0, "b": 1}, "eq_time": 0.6931683230201887}, {"params": {"tau": 0, "D": 0.5256618210139611, "eq_perc": 0.75, "a": 0, "b": 1}, "eq_time": 0.6931683230201887}, {"params": {"tau": 0, "D": 0.08410344094272001, "eq_perc": 0.75, "a": 0, "b": 1}, "eq_time": 0.6931683230201887}, {"params": {"tau": 0, "D": 0.09784391043598925, "eq_perc": 0.75, "a": 0, "b": 1}, "eq_time": 0.6931683230201887}, {"params": {"tau": 0, "D": 0.1206798117697121, "eq_perc": 0.75, "a": 0, "b": 1}, "eq_time": 0.6931683230201887}, {"params": {"tau": 0, "D": 0.15166120982832082, "eq_perc": 0.75, "a": 0, "b": 1}, "eq_time": 0.6931683230201887}, {"params": {"tau": 0, "D": 0.19719702053780838, "eq_perc": 0.75, "a": 0, "b": 1}, "eq_time": 0.6931683230201887}, {"params": {"tau": 0, "D": 0.2726578753868663, "eq_perc": 0.75, "a": 0, "b": 1}, "eq_time": 0.6931683230201887}, {"params": {"tau": 0, "D": 0.42654841787669806, "eq_perc": 0.75, "a": 0, "b": 1}, "eq_time": 0.6931683230201887}, {"params": {"tau": 0, "D": 0.9345099040248201, "eq_perc": 0.75, "a": 0, "b": 1}, "eq_time": 0.6931683230201887}, {"params": {"tau": 0, "D": 0.13141162647300006, "eq_perc": 0.75, "a": 0, "b": 1}, "eq_time": 0.6931683230201887}, {"params": {"tau": 0, "D": 0.1528811100562332, "eq_perc": 0.75, "a": 0, "b": 1}, "eq_time": 0.6931683230201887}, {"params": {"tau": 0, "D": 0.18856220589017514, "eq_perc": 0.75, "a": 0, "b": 1}, "eq_time": 0.6931683230201887}, {"params": {"tau": 0, "D": 0.23697064035675122, "eq_perc": 0.75, "a": 0, "b": 1}, "eq_time": 0.6931683230201887}, {"params": {"tau": 0, "D": 0.30812034459032567, "eq_perc": 0.75, "a": 0, "b": 1}, "eq_time": 0.6931683230201887}, {"params": {"tau": 0, "D": 0.42602793029197866, "eq_perc": 0.75, "a": 0, "b": 1}, "eq_time": 0.6931683230201887}, {"params": {"tau": 0, "D": 0.6664819029323408, "eq_perc": 0.75, "a": 0, "b": 1}, "eq_time": 0.6931683230201887}, {"params": {"tau": 0, "D": 1.4601717250387813, "eq_perc": 0.75, "a": 0, "b": 1}, "eq_time": 0.6931683230201887}, {"params": {"tau": 0, "D": 0.18923274212112007, "eq_perc": 0.75, "a": 0, "b": 1}, "eq_time": 0.6931683230201887}, {"params": {"tau": 0, "D": 0.2201487984809758, "eq_perc": 0.75, "a": 0, "b": 1}, "eq_time": 0.6931683230201887}, {"params": {"tau": 0, "D": 0.27152957648185216, "eq_perc": 0.75, "a": 0, "b": 1}, "eq_time": 0.6931683230201887}, {"params": {"tau": 0, "D": 0.34123772211372183, "eq_perc": 0.75, "a": 0, "b": 1}, "eq_time": 0.6931683230201887}, {"params": {"tau": 0, "D": 0.44369329621006887, "eq_perc": 0.75, "a": 0, "b": 1}, "eq_time": 0.6931683230201887}, {"params": {"tau": 0, "D": 0.6134802196204492, "eq_perc": 0.75, "a": 0, "b": 1}, "eq_time": 0.6931683230201887}, {"params": {"tau": 0, "D": 0.9597339402225705, "eq_perc": 0.75, "a": 0, "b": 1}, "eq_time": 0.6931683230201887}, {"params": {"tau": 0, "D": 2.1026472840558443, "eq_perc": 0.75, "a": 0, "b": 1}, "eq_time": 0.6931683230201887}, {"params": {"tau": 0, "D": 0.25756678788708015, "eq_perc": 0.75, "a": 0, "b": 1}, "eq_time": 0.6931683230201887}, {"params": {"tau": 0, "D": 0.2996469757102171, "eq_perc": 0.75, "a": 0, "b": 1}, "eq_time": 0.6931683230201887}, {"params": {"tau": 0, "D": 0.36958192354474323, "eq_perc": 0.75, "a": 0, "b": 1}, "eq_time": 0.6931683230201887}, {"params": {"tau": 0, "D": 0.4644624550992325, "eq_perc": 0.75, "a": 0, "b": 1}, "eq_time": 0.6931683230201887}, {"params": {"tau": 0, "D": 0.6039158753970384, "eq_perc": 0.75, "a": 0, "b": 1}, "eq_time": 0.6931683230201887}, {"params": {"tau": 0, "D": 0.8350147433722782, "eq_perc": 0.75, "a": 0, "b": 1}, "eq_time": 0.6931683230201887}, {"params": {"tau": 0, "D": 1.3063045297473879, "eq_perc": 0.75, "a": 0, "b": 1}, "eq_time": 0.6931683230201887}, {"params": {"tau": 0, "D": 2.861936581076012, "eq_perc": 0.75, "a": 0, "b": 1}, "eq_time": 0.6931683230201887}, {"params": {"tau": 0, "D": 0.3364137637708802, "eq_perc": 0.75, "a": 0, "b": 1}, "eq_time": 0.6931683230201887}, {"params": {"tau": 0, "D": 0.39137564174395706, "eq_perc": 0.75, "a": 0, "b": 1}, "eq_time": 0.6931683230201887}, {"params": {"tau": 0, "D": 0.4827192470788485, "eq_perc": 0.75, "a": 0, "b": 1}, "eq_time": 0.6931683230201887}, {"params": {"tau": 0, "D": 0.6066448393132833, "eq_perc": 0.75, "a": 0, "b": 1}, "eq_time": 0.6931683230201887}, {"params": {"tau": 0, "D": 0.7887880821512339, "eq_perc": 0.75, "a": 0, "b": 1}, "eq_time": 0.6931683230201887}, {"params": {"tau": 0, "D": 1.0906315015474657, "eq_perc": 0.75, "a": 0, "b": 1}, "eq_time": 0.6931683230201887}, {"params": {"tau": 0, "D": 1.7061936715067931, "eq_perc": 0.75, "a": 0, "b": 1}, "eq_time": 0.6931683230201887}, {"params": {"tau": 0, "D": 3.7380396160992806, "eq_perc": 0.75, "a": 0, "b": 1}, "eq_time": 0.6931683230201887}]